Workbook

Sheet Income Statement
A1: Jack in the box
A2: Income Statement
A3: For the year ended Dec 31, 2024 ($ in 000's)
B4: 2024 | C4: 2023
A5: Sales | B5: 3850000 | C5: 3432000
A6: Cost of Goods Sold | B6: 3250000 | C6: 2864000
A7: Gross Profit | B7: =B5-B6 -> 600000 | C7: =C5-C6 -> 568000
A8: Selling and G&A Expenses | B8: 330300 | C8: 240000
A9: Fixed Expenses | B9: 100000 | C9: 100000
A10: Depreciation Expense | B10: 20000 | C10: 18900
A11: EBIT | B11: =B7-B8-B9-B10 -> 149700 | C11: =C7-C8-C9-C10 -> 209100
A12: Interest Expense | B12: 76000 | C12: 62500
A13: Earnings Before Taxes | B13: =B11-B12 -> 73700 | C13: =C11-C12 -> 146600
A14: Taxes | B14: 18425 | C14: 36650
A15: Net Income | B15: =B13-B14 -> 55275 | C15: =C13-C14 -> 109950
A17: Notes:
A18: Tax Rate | B18: 0.25

Sheet Balance Sheet
A1: Jack in the box
A2: Balance sheet
A3: As of December 31, 2024 ($ in 000's)
A4: Assets | B4: 2024 | C4: 2023
A5: Cash and Equivalents | B5: 52000 | C5: 57600
A6: Accounts Receivable | B6: 402000 | C6: 351200
A7: Inventory | B7: 836000 | C7: 715200
A8: Total Current Assets | B8: =SUM(B5:B7) -> 1290000 | C8: =SUM(C5:C7) -> 1124000
A9: Plant & Equipment | B9: 527000 | C9: 491000
A10: Accumulated Depreciation | B10: 166200 | C10: 146200
A11: Net Fixed Assets | B11: =B9-B10 -> 360800 | C11: =C9-C10 -> 344800
A12: Total Assets | B12: =B8+B11 -> 1650800 | C12: =C8+C11 -> 1468800
A13: Liabilities and Owner’s Equity
A14: Accounts Payable | B14: 175200 | C14: 145600
A15: Short-term Notes Payable | B15: 225000 | C15: 200000
A16: Other Current Liabilities | B16: 140000 | C16: 136000
A17: Total Current Liabilities | B17: =SUM(B14:B16) -> 540200 | C17: =SUM(C14:C16) -> 481600
A18: Long-term Debt | B18: 424612 | C18: 323432
A19: Total Liabilities | B19: =B17+B18 -> 964812 | C19: =C17+C18 -> 805032
A20: Common Stock | B20: 460000 | C20: 460000
A21: Retained Earnings | B21: 225988 | C21: 203768
A22: Total Shareholder’s Equity | B22: =B20+B21 -> 685988 | C22: =C20+C21 -> 663768
A23: Total Liabilities & Owner’s Equity | B23: =B19+B22 -> 1650800 | C23: =C19+C22 -> 1468800

Sheet Common size IS
A1: Jack in the Box
A2: Common-size Income Statement
A3: For the Year Ended Dec. 31, 2024
B4: 2024 | C4: 2023 | E4: Contribution
A5: Sales | B5: ='Income Statement'!B5/'Income Statement'!$B$5 -> 1 | C5: ='Income Statement'!C5/'Income Statement'!$C$5 -> 1
A6: Cost of Goods Sold | B6: ='Income Statement'!B6/'Income Statement'!$B$5 -> 0.84415584 | C6: ='Income Statement'!C6/'Income Statement'!$C$5 -> 0.83449883 | E6: =C6-B6 -> -0.0096570097
A7: Gross Profit | B7: ='Income Statement'!B7/'Income Statement'!$B$5 -> 0.15584416 | C7: ='Income Statement'!C7/'Income Statement'!$C$5 -> 0.16550117
A8: Selling and G&A Expenses | B8: ='Income Statement'!B8/'Income Statement'!$B$5 -> 0.085792208 | C8: ='Income Statement'!C8/'Income Statement'!$C$5 -> 0.06993007 | E8: =C8-B8 -> -0.015862138
A9: Fixed Expenses | B9: ='Income Statement'!B9/'Income Statement'!$B$5 -> 0.025974026 | C9: ='Income Statement'!C9/'Income Statement'!$C$5 -> 0.029137529 | E9: =C9-B9 -> 0.0031635032
A10: Depreciation Expense | B10: ='Income Statement'!B10/'Income Statement'!$B$5 -> 0.0051948052 | C10: ='Income Statement'!C10/'Income Statement'!$C$5 -> 0.005506993 | E10: =C10-B10 -> 0.00031218781
A11: EBIT | B11: ='Income Statement'!B11/'Income Statement'!$B$5 -> 0.038883117 | C11: ='Income Statement'!C11/'Income Statement'!$C$5 -> 0.060926573
A12: Interest Expense | B12: ='Income Statement'!B12/'Income Statement'!$B$5 -> 0.01974026 | C12: ='Income Statement'!C12/'Income Statement'!$C$5 -> 0.018210956 | E12: =C12-B12 -> -0.001529304
A13: Earnings Before Taxes | B13: ='Income Statement'!B13/'Income Statement'!$B$5 -> 0.019142857 | C13: ='Income Statement'!C13/'Income Statement'!$C$5 -> 0.042715618
A14: Taxes | B14: ='Income Statement'!B14/'Income Statement'!$B$5 -> 0.0047857143 | C14: ='Income Statement'!C14/'Income Statement'!$C$5 -> 0.010678904 | E14: =C14-B14 -> 0.0058931901
A15: Net Income | B15: ='Income Statement'!B15/'Income Statement'!$B$5 -> 0.014357143 | C15: ='Income Statement'!C15/'Income Statement'!$C$5 -> 0.032036713 | E15: =SUM(E6:E14) -> -0.01767957

Sheet Common size BS
A1: Jack in the Box
A2: Common-size Balance Sheet
A3: As of Dec. 31, 2024
A4: Assets | B4: 2024 | C4: 2023
A5: Cash and Equivalents | B5: ='Balance Sheet'!B5/'Balance Sheet'!B$12 -> 0.031499879 | C5: ='Balance Sheet'!C5/'Balance Sheet'!C$12 -> 0.039215686
A6: Accounts Receivable | B6: ='Balance Sheet'!B6/'Balance Sheet'!B$12 -> 0.24351829 | C6: ='Balance Sheet'!C6/'Balance Sheet'!C$12 -> 0.23910675
A7: Inventory | B7: ='Balance Sheet'!B7/'Balance Sheet'!B$12 -> 0.50642113 | C7: ='Balance Sheet'!C7/'Balance Sheet'!C$12 -> 0.4869281
A8: Total Current Assets | B8: ='Balance Sheet'!B8/'Balance Sheet'!B$12 -> 0.7814393 | C8: ='Balance Sheet'!C8/'Balance Sheet'!C$12 -> 0.76525054
A9: Plant & Equipment | B9: ='Balance Sheet'!B9/'Balance Sheet'!B$12 -> 0.31923916 | C9: ='Balance Sheet'!C9/'Balance Sheet'!C$12 -> 0.33428649
A10: Accumulated Depreciation | B10: ='Balance Sheet'!B10/'Balance Sheet'!B$12 -> 0.10067846 | C10: ='Balance Sheet'!C10/'Balance Sheet'!C$12 -> 0.099537037
A11: Net Fixed Assets | B11: ='Balance Sheet'!B11/'Balance Sheet'!B$12 -> 0.2185607 | C11: ='Balance Sheet'!C11/'Balance Sheet'!C$12 -> 0.23474946
A12: Total Assets | B12: ='Balance Sheet'!B12/'Balance Sheet'!B$12 -> 1 | C12: ='Balance Sheet'!C12/'Balance Sheet'!C$12 -> 1
A13: Liabilities and Owner’s Equity
A14: Accounts Payable | B14: ='Balance Sheet'!B14/'Balance Sheet'!$B$23 -> 0.10613036 | C14: ='Balance Sheet'!C14/'Balance Sheet'!$C$23 -> 0.09912854
A15: Short-term Notes Payable | B15: ='Balance Sheet'!B15/'Balance Sheet'!$B$23 -> 0.13629755 | C15: ='Balance Sheet'!C15/'Balance Sheet'!$C$23 -> 0.13616558
A16: Other Current Liabilities | B16: ='Balance Sheet'!B16/'Balance Sheet'!$B$23 -> 0.084807366 | C16: ='Balance Sheet'!C16/'Balance Sheet'!$C$23 -> 0.092592593
A17: Total Current Liabilities | B17: ='Balance Sheet'!B17/'Balance Sheet'!$B$23 -> 0.32723528 | C17: ='Balance Sheet'!C17/'Balance Sheet'!$C$23 -> 0.32788671
A18: Long-term Debt | B18: ='Balance Sheet'!B18/'Balance Sheet'!$B$23 -> 0.2572159 | C18: ='Balance Sheet'!C18/'Balance Sheet'!$C$23 -> 0.22020153
A19: Total Liabilities | B19: ='Balance Sheet'!B19/'Balance Sheet'!$B$23 -> 0.58445118 | C19: ='Balance Sheet'!C19/'Balance Sheet'!$C$23 -> 0.54808824
A20: Common Stock | B20: ='Balance Sheet'!B20/'Balance Sheet'!$B$23 -> 0.27865277 | C20: ='Balance Sheet'!C20/'Balance Sheet'!$C$23 -> 0.31318083
A21: Retained Earnings | B21: ='Balance Sheet'!B21/'Balance Sheet'!$B$23 -> 0.13689605 | C21: ='Balance Sheet'!C21/'Balance Sheet'!$B$23 -> 0.12343591
A22: Total Shareholder’s Equity | B22: ='Balance Sheet'!B22/'Balance Sheet'!$B$23 -> 0.41554882 | C22: ='Balance Sheet'!C22/'Balance Sheet'!$C$23 -> 0.45191176
A23: Total Liabilities & Owner’s Equity | B23: ='Balance Sheet'!B23/'Balance Sheet'!$B$23 -> 1 | C23: ='Balance Sheet'!C23/'Balance Sheet'!$C$23 -> 1

Sheet Statement of Cash Flows
A1: Jack in the Box
A2: Statement of Cash Flows
A3: For the Year Ended Dec. 31, 2024 ($ in 000’s)
A4: Cash Flows from Operations
A5: Net Income | B5: ='Income Statement'!B15 -> 55275
A6: Depreciation Expense | B6: ='Income Statement'!B10 -> 20000
A7: Change in Accounts Receivable | B7: ='Balance Sheet'!C6-'Balance Sheet'!B6 -> -50800
A8: Change in Inventories | B8: ='Balance Sheet'!C7-'Balance Sheet'!B7 -> -120800
A9: Change in Accounts Payable | B9: ='Balance Sheet'!B14-'Balance Sheet'!C14 -> 29600
A10: Change in Other Current Liabilities | B10: ='Balance Sheet'!B16-'Balance Sheet'!C16 -> 4000
A11: Total Cash Flows from Operations | C11: =SUM(B5:B10) -> -62725
A12: Cash Flows from Investing
A13: Change in Plant & Equipment | B13: ='Balance Sheet'!C9-'Balance Sheet'!B9 -> -36000
A14: Total Cash Flows from Investing | C14: =B13 -> -36000
A15: Cash Flows from Financing
A16: Change in Short-term Notes Payable | B16: ='Balance Sheet'!B15-'Balance Sheet'!C15 -> 25000
A17: Change in Long-term Debt | B17: ='Balance Sheet'!B18-'Balance Sheet'!C18 -> 101180
A18: Change in Common Stock | B18: ='Balance Sheet'!B20-'Balance Sheet'!C20 -> 0
A19: Cash Dividends Paid to Shareholders | B19: =-('Income Statement'!B15 - ('Balance Sheet'!B21-'Balance Sheet'!C21)) -> -33055
A20: Total Cash Flows from Financing | C20: =SUM(B16:B19) -> 93125
A21: Net Change in Cash Balance

Sheet Common-size Statement Cash Flow
A1: Jack in the Box | E1: Denominator | F1: 1
A2: Statement of Cash Flows
A3: For the Year Ended Dec. 31, 2024 ($ in 000’s)
A4: Cash Flows from Operations | B4: ="% of "&CHOOSE($F$1,"Sales","Beginning Cash") -> % of Sales
A5: Net Income | B5: ='Income Statement'!B15/CHOOSE($F$1,'Income Statement'!$B$5,'Balance Sheet'!$C$5) -> 0.014357143
A6: Depreciation Expense | B6: ='Income Statement'!B10/CHOOSE($F$1,'Income Statement'!$B$5,'Balance Sheet'!$C$5) -> 0.0051948052
A7: Change in Accounts Receivable | B7: =('Balance Sheet'!C6-'Balance Sheet'!B6)/CHOOSE($F$1,'Income Statement'!$B$5,'Balance Sheet'!$C$5) -> -0.013194805
A8: Change in Inventories | B8: =('Balance Sheet'!C7-'Balance Sheet'!B7)/CHOOSE($F$1,'Income Statement'!$B$5,'Balance Sheet'!$C$5) -> -0.031376623
A9: Change in Accounts Payable | B9: =('Balance Sheet'!B14-'Balance Sheet'!C14)/CHOOSE($F$1,'Income Statement'!$B$5,'Balance Sheet'!$C$5) -> 0.0076883117
A10: Change in Other Current Liabilities | B10: =('Balance Sheet'!B16-'Balance Sheet'!C16)/CHOOSE($F$1,'Income Statement'!$B$5,'Balance Sheet'!$C$5) -> 0.001038961
A11: Total Cash Flows from Operations | C11: =SUM(B5:B10) -> -0.016292208
A12: Cash Flows from Investing
A13: Change in Plant & Equipment | B13: =('Balance Sheet'!C9-'Balance Sheet'!B9)/CHOOSE($F$1,'Income Statement'!$B$5,'Balance Sheet'!$C$5) -> -0.0093506494
A14: Total Cash Flows from Investing | C14: =B13 -> -0.0093506494
A15: Cash Flows from Financing
A16: Change in Short-term Notes Payable | B16: =('Balance Sheet'!B15-'Balance Sheet'!C15)/CHOOSE($F$1,'Income Statement'!$B$5,'Balance Sheet'!$C$5) -> 0.0064935065
A17: Change in Long-term Debt | B17: =('Balance Sheet'!B18-'Balance Sheet'!C18)/CHOOSE($F$1,'Income Statement'!$B$5,'Balance Sheet'!$C$5) -> 0.026280519
A18: Change in Common Stock | B18: =('Balance Sheet'!B20-'Balance Sheet'!C20)/CHOOSE($F$1,'Income Statement'!$B$5,'Balance Sheet'!$C$5) -> 0
A19: Cash Dividends Paid to Shareholders | B19: =-('Income Statement'!B15 - ('Balance Sheet'!B21-'Balance Sheet'!C21))/ CHOOSE($F$1,'Income Statement'!$B$5,'Balance Sheet'!$C$5) -> -0.0085857143
A20: Total Cash Flows from Financing | C20: =SUM(B16:B19) -> 0.024188312
A21: Net Change in Cash Balance | C21: =SUM(C11:C20) -> -0.0014545455

Sheet Ratios
A1: Jack in the Box
A2: Ratio Analysis for 2023 and 2024
A3: Ratio | B3: 2024 | C3: 2023 | D3: Industry 2024 | E3: Analysis
A4: Liquidity Ratios
A5: Current Ratio | B5: ='Balance Sheet'!B8/'Balance Sheet'!B17 -> 2.3880044 | C5: ='Balance Sheet'!C8/'Balance Sheet'!C17 -> 2.333887 | D5: 2.7 | E5: =IF(AND(B5/C5>=1,B5/ D5>=1),"Good",IF(OR(B5/D5>=1,B5/C5>=1),"Ok","Bad")) -> Ok
A6: Quick Ratio | B6: =('Balance Sheet'!B8-'Balance Sheet'!B7)/'Balance Sheet'!B17 -> 0.84042947 | C6: =('Balance Sheet'!C8-'Balance Sheet'!C7)/'Balance Sheet'!C17 -> 0.84883721 | D6: 1 | E6: =IF(AND(B6/C6>=1,B6/ D6>=1),"Good",IF(OR(B6/D6>=1,B6/C6>=1),"Ok","Bad")) -> Bad
A7: Efficancy Ratios
A8: Inventory Turnover | B8: ='Income Statement'!B6/'Balance Sheet'!B7 -> 3.8875598 | C8: ='Income Statement'!C6/'Balance Sheet'!C7 -> 4.0044743 | D8: 7 | E8: =IF(AND(B8/C8>=1,B8/ D8>=1),"Good",IF(OR(B8/D8>=1,B8/C8>=1),"Ok","Bad")) -> Bad
A9: A/R Turnover | B9: ='Income Statement'!B5/'Balance Sheet'!B6 -> 9.5771144 | C9: ='Income Statement'!C5/'Balance Sheet'!C6 -> 9.7722096 | D9: 10.7 | E9: =IF(AND(B9/C9>=1,B9/ D9>=1),"Good",IF(OR(B9/D9>=1,B9/C9>=1),"Ok","Bad")) -> Bad
A10: Average Collection Period | B10: ='Balance Sheet'!B6/('Income Statement'!B5/360) -> 37.58961 | C10: ='Balance Sheet'!C6/('Income Statement'!C5/360) -> 36.839161 | D10: 33.64 | E10: =IF(AND(B10/C10>=1,B10/ D10>=1),"Good",IF(OR(B10/D10>=1,B10/C10>=1),"Ok","Bad")) -> Good
A11: Fixed Asset Turnover | B11: ='Income Statement'!B5/'Balance Sheet'!B11 -> 10.670732 | C11: ='Income Statement'!C5/'Balance Sheet'!C11 -> 9.9535963 | D11: 11.2 | E11: =IF(AND(B11/C11>=1,B11/ D11>=1),"Good",IF(OR(B11/D11>=1,B11/C11>=1),"Ok","Bad")) -> Ok
A12: Total Asset Turnover | B12: ='Income Statement'!B5/'Balance Sheet'!B12 -> 2.3322026 | C12: ='Income Statement'!C5/'Balance Sheet'!C12 -> 2.3366013 | D12: 2.6 | E12: =IF(AND(B12/C12>=1,B12/ D12>=1),"Good",IF(OR(B12/D12>=1,B12/C12>=1),"Ok","Bad")) -> Bad
A13: Leverage Ratios
A14: Total Debt Ratio | B14: ='Balance Sheet'!B19/'Balance Sheet'!B12 -> 0.58445118 | C14: ='Balance Sheet'!C19/'Balance Sheet'!C12 -> 0.54808824 | D14: 0.5 | E14: =IF(AND(B14/C14>=1,B14/ D14>=1),"Good",IF(OR(B14/D14>=1,B14/C14>=1),"Ok","Bad")) -> Good
A15: Long-term Debt Ratio | B15: ='Balance Sheet'!B18/'Balance Sheet'!B12 -> 0.2572159 | C15: ='Balance Sheet'!C18/'Balance Sheet'!C12 -> 0.22020153 | D15: 0.2 | E15: =IF(AND(B15/C15>=1,B15/ D15>=1),"Good",IF(OR(B15/D15>=1,B15/C15>=1),"Ok","Bad")) -> Good
A16: Long-Term Debt to Total Capitalization Ratio | B16: ='Balance Sheet'!B18/('Balance Sheet'!B18+'Balance Sheet'!B22) -> 0.38232667 | C16: ='Balance Sheet'!C18/('Balance Sheet'!C18+'Balance Sheet'!C22) -> 0.32762561 | D16: 0.2857 | E16: =IF(AND(B16/C16>=1,B16/ D16>=1),"Good",IF(OR(B16/D16>=1,B16/C16>=1),"Ok","Bad")) -> Good
A17: Debt to Equity Ratio | B17: ='Balance Sheet'!B19/'Balance Sheet'!B22 -> 1.4064561 | C17: ='Balance Sheet'!B19/'Balance Sheet'!B22 -> 1.4064561 | D17: 1 | E17: =IF(AND(B17/C17>=1,B17/ D17>=1),"Good",IF(OR(B17/D17>=1,B17/C17>=1),"Ok","Bad")) -> Good
A18: Long-Term Debt to Equity Ratio | B18: ='Balance Sheet'!B18/'Balance Sheet'!B22 -> 0.61897876 | C18: ='Balance Sheet'!C18/'Balance Sheet'!C22 -> 0.48726664 | D18: 0.4 | E18: =IF(AND(B18/C18>=1,B18/ D18>=1),"Good",IF(OR(B18/D18>=1,B18/C18>=1),"Ok","Bad")) -> Good
A19: Coverage Ratios
A20: Times Interest Ratio | B20: ='Income Statement'!B11/'Income Statement'!B12 -> 1.9697368 | C20: ='Income Statement'!C11/'Income Statement'!C12 -> 3.3456 | D20: 2.5 | E20: =IF(AND(B20/C20>=1,B20/ D20>=1),"Good",IF(OR(B20/D20>=1,B20/C20>=1),"Ok","Bad")) -> Bad
A21: Cash Coverage Ratio | B21: =('Income Statement'!B11+'Income Statement'!B10)/'Income Statement'!B12 -> 2.2328947 | C21: =('Income Statement'!C11+'Income Statement'!C10)/'Income Statement'!C12 -> 3.648 | D21: 2.8 | E21: =IF(AND(B21/C21>=1,B21/ D21>=1),"Good",IF(OR(B21/D21>=1,B21/C21>=1),"Ok","Bad")) -> Bad
A22: Profitability Ratios
A23: Gross Profit Ratio | B23: ='Income Statement'!B7/'Income Statement'!B5 -> 0.15584416 | C23: ='Income Statement'!C7/'Income Statement'!C5 -> 0.16550117 | D23: 0.175 | E23: =IF(AND(B23/C23>=1,B23/ D23>=1),"Good",IF(OR(B23/D23>=1,B23/C23>=1),"Ok","Bad")) -> Bad
A24: Opporating Profit | B24: ='Income Statement'!B11/'Income Statement'!B5 -> 0.038883117 | C24: ='Income Statement'!C11/'Income Statement'!C5 -> 0.060926573 | D24: 0.0625 | E24: =IF(AND(B24/C24>=1,B24/ D24>=1),"Good",IF(OR(B24/D24>=1,B24/C24>=1),"Ok","Bad")) -> Bad
A25: Net Profit Margin | B25: ='Income Statement'!B15/'Income Statement'!B5 -> 0.014357143 | C25: ='Income Statement'!C15/'Income Statement'!C5 -> 0.032036713 | D25: 0.035 | E25: =IF(AND(B25/C25>=1,B25/ D25>=1),"Good",IF(OR(B25/D25>=1,B25/C25>=1),"Ok","Bad")) -> Bad
A26: Return on Total Assets | B26: ='Income Statement'!B15/'Balance Sheet'!B12 -> 0.033483765 | C26: ='Income Statement'!C15/'Balance Sheet'!C12 -> 0.074857026 | D26: 0.091 | E26: =IF(AND(B26/C26>=1,B26/ D26>=1),"Good",IF(OR(B26/D26>=1,B26/C26>=1),"Ok","Bad")) -> Bad
A27: Return on Equity | B27: ='Income Statement'!B15/'Balance Sheet'!B22 -> 0.080577211 | C27: ='Income Statement'!C15/'Balance Sheet'!C22 -> 0.16564523 | D27: 0.182 | E27: =IF(AND(B27/C27>=1,B27/ D27>=1),"Good",IF(OR(B27/D27>=1,B27/C27>=1),"Ok","Bad")) -> Bad
A28: Return on Common Equity | B28: ='Income Statement'!B15/'Balance Sheet'!B22 -> 0.080577211 | C28: ='Income Statement'!C15/'Balance Sheet'!C22 -> 0.16564523 | D28: 0.182 | E28: =IF(AND(B28/C28>=1,B28/ D28>=1),"Good",IF(OR(B28/D28>=1,B28/C28>=1),"Ok","Bad")) -> Bad
A30: DuPoint ROE | B30: =(B25*B12)/(1-B14) -> 0.080577211 | C30: =(C25*C12)/(1-C14) -> 0.16564523
A31: Market Value of Equity | B31: 1105500

Sheet Economic Profit
A1: Jack in the Box
A2: Economic Profit Calculations
B3: 2020 | C3: 2019
A4: Tax Rate | B4: ='Income Statement'!$B18 -> 0.25 | C4: ='Income Statement'!$B18 -> 0.25
A5: NOPAT | B5: ='Income Statement'!B11*(1-B4) -> 112275 | C5: ='Income Statement'!C11*(1-C4) -> 156825
A6: Total Operating Capital | B6: ='Balance Sheet'!B8+'Balance Sheet'!B11-('Balance Sheet'!B17-'Balance Sheet'!B15) -> 1335600 | C6: ='Balance Sheet'!C8+'Balance Sheet'!C11-('Balance Sheet'!C17-'Balance Sheet'!C15) -> 1187200
A7: After-tax WACC | B7: 0.13 | C7: 0.13
A8: Dollar WACC | B8: =B6*B7 -> 173628 | C8: =C6*C7 -> 154336
A9: Economic Profit | B9: =B5-B8 -> -61353 | C9: =C5-C8 -> 2489

Sheet Sheet1
A1: Elvis Products International
A2: Ratio Analysis for 2019 and 2020
A3: Ratio | B3: 2020 | C3: 2019
A4: Liquidity Ratios
A5: Inventory Turnover | B5: 3.89x | C5: 4.00x
A6: A/R Turnover | B6: 9.58x | C6: 9.77x
A7: Average Collection Period | B7: 37.59 days | C7: 36.84 days
A8: Fixed Asset Turnover | B8: 10.67x | C8: 9.95x
A9: Total Asset Turnover | B9: 2.33x | C9: 2.34x

Sheet Common-size statement of cash
A1: Elvis Products International
A2: Common-size Statement of Cash Flows
A3: For the Year Ended Dec. 31, 2024
A4: Cash Flows from Operations | B4: % of Sales
A5: Net Income | B5: ='Income Statement'!B15/'Income Statement'!B$5 -> 0.014357143
A6: Depreciation Expense | B6: ='Income Statement'!B10/'Income Statement'!B$5 -> 0.0051948052
A7: Change in Accounts Receivable | B7: ='Income Statement'!B17/'Income Statement'!B$5 -> 0
A8: Change in Inventories | B8: ='Income Statement'!B18/'Income Statement'!B$5 -> 6.4935065e-08
A9: Change in Accounts Payable | B9: ='Income Statement'!B19/'Income Statement'!B$5 -> 0
A10: Change in Other Current Liabilities | B10: ='Income Statement'!B20/'Income Statement'!B$5 -> 0
A11: Total Cash Flows from Operations | C11: -0.0163
A12: Cash Flows from Investing
A13: Change in Plant & Equipment | B13: -0.0094
A14: Total Cash Flows from Investing | C14: -0.0094
A15: Cash Flows from Financing
A16: Change in Short-term Notes Payable | B16: 0.0065
A17: Change in Long-term Debt | B17: 0.0263
A18: Change in Common Stock | B18: 0
A19: Cash Dividends Paid to Shareholders | B19: -0.0086
A20: Total Cash Flows from Financing | C20: 0.0242
A21: Net Change in Cash Balance | C21: -0.0015
